{
  "result": [
    {
      "id": 1,
      "no": 1,
      "name": "David De Gea",
      "birth_date": "1990-11-07",
      "Position": "Goalkeeper",
      "International": "Spain",
      "Team": "Manchester United",
      "Poster": "http://www.manutd.com/sitecore/shell/~/media/C52DB6DA5F2A421EBD03335A07F8270E.ashx?w=240&h=311&rgn=0,106,2000,2700"
    },
    {
      "id": 2,
      "no": 2,
      "name": "Victor Lindelov",
      "birth_date": "1994-07-17",
      "Position": "Defender",
      "International": "Sweden",
      "Team": "Manchester United",
      "Poster": "http://www.manutd.com/sitecore/shell/~/media/D904E5EEAC6042F3BC96FE1CCD1688E6.ashx?w=240&h=311&rgn=167,0,2186,2613"
    },
    {
      "id": 3,
      "no": 3,
      "name": "Erick Bailly",
      "birth_date": "1994-04-12",
      "Position": "Defender",
      "International": "Ivory Coast",
      "Team": "Manchester United",
      "Poster": "http://www.manutd.com/sitecore/shell/~/media/C0DC1E0849F54882852AB54A9E6645E9.ashx?w=240&h=311&rgn=593,93,1233,920"
    },
    {
      "id": 4,
      "no": 4,
      "name": "Phil Jones",
      "birth_date": "1992-02-21",
      "Position": "Defender",
      "International": "England",
      "Team": "Manchester United",
      "Poster": "http://www.manutd.com/sitecore/shell/~/media/86FBC5F87D844A0B976BD491D7FBB1EE.ashx?w=240&h=311&rgn=0,133,2000,2726"
    },
    {
      "id": 5,
      "no": 5,
      "name": "Marcos Rojo",
      "birth_date": "1990-03-20",
      "Position": "Defender",
      "International": "Argentina",
      "Team": "Manchester United",
      "Poster": "http://www.manutd.com/sitecore/shell/~/media/A1958ED78E654F56B036532A39E5EBA1.ashx?w=240&h=311&rgn=0,0,2000,2595"
    },
    {
      "id": 6,
      "no": 6,
      "name": "Paul Pogba",
      "birth_date": "1993-03-15",
      "Position": "MidFielder",
      "International": "France",
      "Team": "Manchester United",
      "Poster": "http://www.manutd.com/sitecore/shell/~/media/D90FDAF01B034317B8D701F315C30E22.ashx?w=240&h=311&rgn=0,206,2000,2800"
    },
    {
      "id": 7,
      "no": 7,
      "name": "Alexis",
      "birth_date": "1988-12-19",
      "Position": "Forward",
      "International": "Chile",
      "Team": "Manchester United",
      "Poster": "http://www.manutd.com/sitecore/shell/~/media/6F8B56D0E075411EB7185186B95A2205.ashx?w=240&h=311&rgn=0,0,3840,4979"
    },
    {
      "id": 8,
      "no": 8,
      "name": "Juan Mata",
      "birth_date": "1988-04-28",
      "Position": "Attacking MidFielder",
      "International": "Spain",
      "Team": "Manchester United",
      "Poster": "http://www.manutd.com/sitecore/shell/~/media/6736E489D9F8480DBABD40F33B60A398.ashx?w=240&h=311&rgn=333,120,1626,1800"
    },
    {
      "id": 9,
      "no": 9,
      "name": "Romelu Lukaku",
      "birth_date": "1993-05-13",
      "Position": "Striker",
      "International": "Belgium",
      "Team": "Manchester United",
      "Poster": "http://www.manutd.com/sitecore/shell/~/media/D6551FB29FE74D7B97AFAD9C94AEECD0.ashx?w=240&h=311&rgn=0,55,1500,2000"
    },
    {
      "id": 10,
      "no": 11,
      "name": "Anthony Martial",
      "birth_date": "1995-12-05",
      "Position": "Striker",
      "International": "France",
      "Team": "Manchester United",
      "Poster": "http://www.manutd.com/sitecore/shell/~/media/BE1FCE0096BC449CAA2802EFE0231A02.ashx?w=240&h=311&rgn=0,0,5242,6802"
    },
    {
      "id": 11,
      "no": 12,
      "name": "Chris Smalling",
      "birth_date": "1989-11-22",
      "Position": "Defender",
      "International": "England",
      "Team": "Manchester United",
      "Poster": "http://www.manutd.com/sitecore/shell/~/media/938F31BD08DD4FC681D0FA58C50DCBD6.ashx?w=240&h=311&rgn=0,0,2000,2593"
    },
    {
      "id": 12,
      "no": 14,
      "name": "Jesse Lingard",
      "birth_date": "1992-12-15",
      "Position": "MidFielder",
      "International": "England",
      "Team": "Manchester United",
      "Poster": "http://www.manutd.com/sitecore/shell/~/media/52515288EA844268803C1FAA8004C2BF.ashx?w=240&h=311&rgn=180,40,1686,1993"
    },
    {
      "id": 13,
      "no": 40,
      "name": "joel Pereira",
      "birth_date": "1996-01-01",
      "Position": "Goal Keeper",
      "International": "Portugal",
      "Team": "Manchester United",
      "Poster": "http://www.manutd.com/sitecore/shell/~/media/2E9620F49612493390248FA23E93EF11.ashx?w=240&h=311&rgn=41,0,1730,2188"
    },
    {
      "id": 14,
      "no": 19,
      "name": "Marcus Rashford",
      "birth_date": "1997-02-02",
      "Position": "Forward",
      "International": "England",
      "Team": "Manchester United",
      "Poster": "http://www.manutd.com/sitecore/shell/~/media/A1B82B086BF8474AA6546A96BA3EC623.ashx?w=240&h=311&rgn=697,0,2291,2062"
    }
  ]
}
